jupyter_collaboration/__init__.py
jupyter_collaboration/_version.py
jupyter_collaboration-4.1.2.dist-info/METADATA
jupyter_collaboration-4.1.2.dist-info/WHEEL
jupyter_collaboration-4.1.2.dist-info/licenses/LICENSE
jupyter_collaboration-4.1.2.dist-info/RECORD
